README.md
setup.cfg
setup.py
src/lima_toolbox.egg-info/PKG-INFO
src/lima_toolbox.egg-info/SOURCES.txt
src/lima_toolbox.egg-info/dependency_links.txt
src/lima_toolbox.egg-info/entry_points.txt
src/lima_toolbox.egg-info/requires.txt
src/lima_toolbox.egg-info/top_level.txt
src/limatb/__init__.py
src/limatb/__main__.py
src/limatb/acquire.py
src/limatb/cli.py
src/limatb/info.py
src/limatb/network.py
src/limatb/util.py