Metadata-Version: 2.1
Name: lima-toolbox
Version: 1.0.0
Summary: Lima toolbox
Home-page: https://github.com/tiagocoutinho/lima-toolbox
Author: Jose Tiago Macara Coutinho
Author-email: coutinhotiago@gmail.com
License: UNKNOWN
Keywords: Lima,CLI,toolbox,detector
Platform: UNKNOWN
Classifier: Development Status :: 2 - Pre-Alpha
Classifier: Intended Audience :: Developers
Classifier: Natural Language :: English
Classifier: Programming Language :: Python :: 3.5
Classifier: Programming Language :: Python :: 3.6
Classifier: Programming Language :: Python :: 3.7
Classifier: License :: OSI Approved :: GNU General Public License v3 (GPLv3)
Requires-Python: >=3.5
Provides-Extra: basler
Provides-Extra: eiger
Provides-Extra: all
